{"games":[{"board":"rnb1kbnr/pppp1ppp/8/4p3/6Pq/5P2/PPPPP2P/RNBQKBNR w KQkq - 1 3","timeStamp":1674396478875,"result":"CheckMate"},{"board":"rnb1kbnr/pppp1ppp/8/4p3/6Pq/5P2/PPPPP2P/RNBQKBNR w KQkq - 1 3","timeStamp":1674396546698,"result":"CheckMate"},{"board":"8/p6p/5k2/8/3K4/2rq4/8/8 w - - 4 12","timeStamp":1674401238435,"result":"CheckMate"},{"board":"8/8/p6p/K1k5/1p6/r7/P7/8 w - 3-123 4 27","timeStamp":1674406695117,"result":"CheckMate"},{"board":"8/4q3/1q5K/8/6k1/8/8/8 w - 3-123 6 28","timeStamp":1674406727043,"result":"CheckMate"},{"board":"8/p7/8/4k3/1p6/1B3K1q/P5r1/8 w - 3-123 4 15","timeStamp":1674406748386,"result":"CheckMate"},{"board":"4R1k1/6r1/3p2Q1/7p/3p3q/3P4/PP1N1P2/5RK1 b - 3-123 5 29","timeStamp":1674406918396,"result":"CheckMate"}]}